[{"source":575,"target":574},{"source":573,"target":575},{"source":572,"target":575},{"source":571,"target":575},{"source":570,"target":575},{"source":569,"target":575},{"source":568,"target":567},{"source":568,"target":566},{"source":568,"target":565},{"source":564,"target":565},{"source":563,"target":562},{"source":564,"target":561},{"source":560,"target":559},{"source":560,"target":558},{"source":557,"target":556},{"source":557,"target":555},{"source":557,"target":554},{"source":564,"target":553},{"source":557,"target":552},{"source":557,"target":560},{"source":551,"target":560},{"source":557,"target":550},{"source":564,"target":549},{"source":551,"target":557},{"source":548,"target":557},{"source":547,"target":557},{"source":546,"target":557},{"source":545,"target":557},{"source":544,"target":557},{"source":564,"target":543},{"source":546,"target":564},{"source":542,"target":564},{"source":541,"target":564},{"source":572,"target":540},{"source":539,"target":574},{"source":538,"target":537},{"source":536,"target":535},{"source":538,"target":534},{"source":533,"target":572},{"source":532,"target":572},{"source":539,"target":531},{"source":539,"target":530},{"source":570,"target":538},{"source":532,"target":538},{"source":529,"target":538},{"source":528,"target":538},{"source":564,"target":538},{"source":527,"target":539},{"source":526,"target":539},{"source":528,"target":539},{"source":525,"target":524},{"source":563,"target":523},{"source":522,"target":521},{"source":534,"target":521},{"source":568,"target":521},{"source":520,"target":521},{"source":519,"target":521},{"source":528,"target":521},{"source":518,"target":521},{"source":517,"target":540},{"source":537,"target":516},{"source":515,"target":516},{"source":514,"target":513},{"source":512,"target":511},{"source":563,"target":510},{"source":517,"target":509},{"source":508,"target":507},{"source":517,"target":506},{"source":505,"target":530},{"source":504,"target":530},{"source":503,"target":502},{"source":501,"target":500},{"source":499,"target":498},{"source":497,"target":512},{"source":496,"target":512},{"source":495,"target":512},{"source":494,"target":497},{"source":493,"target":492},{"source":499,"target":491},{"source":490,"target":491},{"source":489,"target":491},{"source":488,"target":499},{"source":487,"target":486},{"source":494,"target":485},{"source":490,"target":484},{"source":483,"target":561},{"source":482,"target":561},{"source":508,"target":561},{"source":556,"target":561},{"source":481,"target":561},{"source":480,"target":479},{"source":508,"target":570},{"source":519,"target":570},{"source":478,"target":477},{"source":501,"target":476},{"source":475,"target":474},{"source":490,"target":474},{"source":553,"target":483},{"source":473,"target":482},{"source":472,"target":482},{"source":471,"target":470},{"source":472,"target":469},{"source":472,"target":468},{"source":467,"target":466},{"source":465,"target":493},{"source":464,"target":465},{"source":463,"target":465},{"source":462,"target":464},{"source":461,"target":464},{"source":463,"target":464},{"source":517,"target":460},{"source":459,"target":508},{"source":526,"target":508},{"source":458,"target":508},{"source":457,"target":508},{"source":547,"target":556},{"source":461,"target":462},{"source":456,"target":462},{"source":455,"target":462},{"source":454,"target":462},{"source":453,"target":462},{"source":452,"target":462},{"source":518,"target":519},{"source":553,"target":480},{"source":552,"target":553},{"source":547,"target":553},{"source":546,"target":553},{"source":451,"target":450},{"source":449,"target":448},{"source":447,"target":448},{"source":446,"target":461},{"source":445,"target":444},{"source":443,"target":442},{"source":441,"target":487},{"source":440,"target":439},{"source":438,"target":443},{"source":437,"target":443},{"source":436,"target":443},{"source":435,"target":445},{"source":547,"target":434},{"source":455,"target":433},{"source":432,"target":431},{"source":547,"target":430},{"source":463,"target":429},{"source":489,"target":428},{"source":427,"target":426},{"source":425,"target":424},{"source":463,"target":514},{"source":423,"target":514},{"source":422,"target":475},{"source":501,"target":475},{"source":421,"target":420},{"source":419,"target":420},{"source":418,"target":420},{"source":417,"target":420},{"source":432,"target":416},{"source":455,"target":446},{"source":415,"target":446},{"source":463,"target":446},{"source":454,"target":446},{"source":414,"target":446},{"source":413,"target":446},{"source":427,"target":412},{"source":451,"target":421},{"source":489,"target":411},{"source":501,"target":411},{"source":489,"target":422},{"source":501,"target":422},{"source":432,"target":410},{"source":490,"target":409},{"source":408,"target":407},{"source":503,"target":406},{"source":405,"target":490},{"source":489,"target":490},{"source":404,"target":547},{"source":481,"target":547},{"source":544,"target":547},{"source":455,"target":403},{"source":415,"target":455},{"source":503,"target":455},{"source":402,"target":455},{"source":401,"target":455},{"source":452,"target":455},{"source":463,"target":415},{"source":503,"target":415},{"source":400,"target":463},{"source":454,"target":463},{"source":399,"target":463},{"source":398,"target":463},{"source":397,"target":396},{"source":395,"target":503},{"source":454,"target":503},{"source":399,"target":503},{"source":432,"target":503},{"source":417,"target":503},{"source":394,"target":503},{"source":413,"target":503},{"source":397,"target":393},{"source":432,"target":473},{"source":432,"target":402},{"source":392,"target":391},{"source":432,"target":453},{"source":414,"target":432},{"source":390,"target":432},{"source":452,"target":432},{"source":397,"target":414},{"source":389,"target":388},{"source":387,"target":388},{"source":427,"target":387},{"source":386,"target":472},{"source":385,"target":427},{"source":384,"target":427},{"source":383,"target":427},{"source":383,"target":385},{"source":489,"target":382},{"source":386,"target":381},{"source":501,"target":489},{"source":380,"target":379},{"source":378,"target":572},{"source":378,"target":538},{"source":378,"target":532},{"source":378,"target":377},{"source":376,"target":378},{"source":458,"target":375},{"source":374,"target":373},{"source":523,"target":374},{"source":372,"target":374},{"source":371,"target":370},{"source":369,"target":368},{"source":367,"target":368},{"source":458,"target":531},{"source":459,"target":533},{"source":458,"target":366},{"source":528,"target":366},{"source":528,"target":365},{"source":560,"target":459},{"source":518,"target":459},{"source":364,"target":459},{"source":367,"target":363},{"source":362,"target":361},{"source":458,"target":362},{"source":557,"target":362},{"source":360,"target":362},{"source":359,"target":362},{"source":528,"target":526},{"source":358,"target":357},{"source":443,"target":358},{"source":356,"target":358},{"source":355,"target":358},{"source":356,"target":369},{"source":354,"target":369},{"source":353,"target":369},{"source":367,"target":438},{"source":564,"target":458},{"source":549,"target":352},{"source":552,"target":559},{"source":550,"target":559},{"source":351,"target":559},{"source":350,"target":559},{"source":549,"target":559},{"source":349,"target":559},{"source":348,"target":559},{"source":544,"target":559},{"source":347,"target":558},{"source":346,"target":556},{"source":347,"target":345},{"source":444,"target":344},{"source":549,"target":554},{"source":350,"target":343},{"source":541,"target":350},{"source":549,"target":342},{"source":349,"target":549},{"source":341,"target":549},{"source":544,"target":549},{"source":347,"target":340},{"source":347,"target":339},{"source":338,"target":337},{"source":336,"target":337},{"source":529,"target":569},{"source":335,"target":334},{"source":469,"target":334},{"source":461,"target":334},{"source":333,"target":521},{"source":332,"target":522},{"source":331,"target":368},{"source":330,"target":513},{"source":329,"target":328},{"source":423,"target":328},{"source":365,"target":534},{"source":327,"target":534},{"source":326,"target":534},{"source":325,"target":534},{"source":324,"target":332},{"source":323,"target":332},{"source":507,"target":322},{"source":360,"target":321},{"source":320,"target":507},{"source":376,"target":507},{"source":333,"target":319},{"source":318,"target":317},{"source":316,"target":315},{"source":431,"target":314},{"source":313,"target":314},{"source":329,"target":312},{"source":311,"target":329},{"source":310,"target":329},{"source":470,"target":329},{"source":469,"target":329},{"source":468,"target":329},{"source":419,"target":329},{"source":386,"target":329},{"source":309,"target":308},{"source":307,"target":310},{"source":330,"target":310},{"source":306,"target":477},{"source":305,"target":477},{"source":304,"target":477},{"source":402,"target":303},{"source":302,"target":301},{"source":316,"target":301},{"source":300,"target":365},{"source":299,"target":298},{"source":297,"target":298},{"source":296,"target":298},{"source":295,"target":559},{"source":294,"target":327},{"source":564,"target":327},{"source":293,"target":327},{"source":564,"target":292},{"source":291,"target":326},{"source":290,"target":326},{"source":289,"target":326},{"source":330,"target":288},{"source":518,"target":526},{"source":364,"target":526},{"source":376,"target":300},{"source":423,"target":461},{"source":295,"target":504},{"source":564,"target":504},{"source":295,"target":560},{"source":423,"target":433},{"source":287,"target":431},{"source":423,"target":431},{"source":421,"target":286},{"source":423,"target":286},{"source":285,"target":284},{"source":283,"target":284},{"source":421,"target":284},{"source":287,"target":284},{"source":282,"target":283},{"source":295,"target":376},{"source":402,"target":307},{"source":423,"target":307},{"source":417,"target":307},{"source":281,"target":280},{"source":295,"target":549},{"source":360,"target":557},{"source":421,"target":279},{"source":287,"target":421},{"source":278,"target":421},{"source":399,"target":421},{"source":277,"target":421},{"source":276,"target":421},{"source":423,"target":421},{"source":296,"target":421},{"source":275,"target":421},{"source":364,"target":333},{"source":274,"target":281},{"source":398,"target":281},{"source":423,"target":281},{"source":339,"target":295},{"source":548,"target":295},{"source":541,"target":295},{"source":364,"target":518},{"source":273,"target":407},{"source":272,"target":407},{"source":419,"target":271},{"source":454,"target":419},{"source":423,"target":419},{"source":401,"target":419},{"source":270,"target":419},{"source":402,"target":406},{"source":423,"target":406},{"source":454,"target":269},{"source":452,"target":403},{"source":274,"target":268},{"source":402,"target":268},{"source":316,"target":267},{"source":274,"target":266},{"source":402,"target":266},{"source":402,"target":274},{"source":265,"target":274},{"source":423,"target":395},{"source":399,"target":264},{"source":402,"target":263},{"source":399,"target":454},{"source":277,"target":454},{"source":417,"target":454},{"source":402,"target":399},{"source":423,"target":277},{"source":275,"target":402},{"source":423,"target":398},{"source":453,"target":423},{"source":262,"target":423},{"source":452,"target":401},{"source":261,"target":282},{"source":261,"target":270},{"source":452,"target":453},{"source":260,"target":259},{"source":258,"target":259},{"source":257,"target":261},{"source":309,"target":256},{"source":255,"target":540},{"source":255,"target":516},{"source":319,"target":322},{"source":319,"target":573},{"source":319,"target":572},{"source":539,"target":319},{"source":532,"target":319},{"source":532,"target":255},{"source":254,"target":565},{"source":253,"target":252},{"source":251,"target":254},{"source":544,"target":250},{"source":556,"target":249},{"source":543,"target":248},{"source":543,"target":247},{"source":246,"target":245},{"source":482,"target":245},{"source":556,"target":245},{"source":542,"target":245},{"source":544,"target":245},{"source":552,"target":246},{"source":430,"target":246},{"source":244,"target":243},{"source":552,"target":352},{"source":550,"target":558},{"source":242,"target":558},{"source":432,"target":558},{"source":241,"target":558},{"source":556,"target":240},{"source":552,"target":556},{"source":550,"target":556},{"source":239,"target":556},{"source":238,"target":556},{"source":434,"target":237},{"source":550,"target":237},{"source":236,"target":237},{"source":446,"target":237},{"source":342,"target":237},{"source":463,"target":237},{"source":242,"target":237},{"source":241,"target":237},{"source":235,"target":234},{"source":357,"target":363},{"source":233,"target":555},{"source":430,"target":232},{"source":550,"target":232},{"source":342,"target":232},{"source":552,"target":231},{"source":351,"target":480},{"source":438,"target":230},{"source":438,"target":444},{"source":229,"target":552},{"source":430,"target":552},{"source":351,"target":552},{"source":235,"target":552},{"source":348,"target":552},{"source":544,"target":552},{"source":413,"target":552},{"source":543,"target":434},{"source":481,"target":434},{"source":544,"target":434},{"source":342,"target":229},{"source":551,"target":430},{"source":349,"target":430},{"source":542,"target":430},{"source":228,"target":351},{"source":544,"target":351},{"source":227,"target":226},{"source":543,"target":226},{"source":543,"target":225},{"source":336,"target":225},{"source":228,"target":446},{"source":543,"target":342},{"source":336,"target":455},{"source":543,"target":503},{"source":239,"target":543},{"source":423,"target":543},{"source":544,"target":543},{"source":224,"target":543},{"source":481,"target":253},{"source":544,"target":253},{"source":238,"target":481},{"source":223,"target":242},{"source":228,"target":223},{"source":545,"target":228},{"source":241,"target":228},{"source":224,"target":336},{"source":457,"target":567},{"source":562,"target":373},{"source":222,"target":368},{"source":320,"target":568},{"source":221,"target":568},{"source":220,"target":510},{"source":376,"target":320},{"source":290,"target":219},{"source":457,"target":218},{"source":217,"target":363},{"source":216,"target":215},{"source":564,"target":221},{"source":457,"target":361},{"source":356,"target":214},{"source":217,"target":214},{"source":217,"target":449},{"source":356,"target":443},{"source":220,"target":217},{"source":355,"target":217},{"source":564,"target":290},{"source":457,"target":289},{"source":557,"target":376},{"source":457,"target":350},{"source":457,"target":549},{"source":404,"target":457},{"source":359,"target":457},{"source":574,"target":521},{"source":574,"target":540},{"source":534,"target":540},{"source":568,"target":540},{"source":530,"target":540},{"source":508,"target":540},{"source":326,"target":540},{"source":458,"target":540},{"source":527,"target":332},{"source":324,"target":573},{"source":515,"target":573},{"source":376,"target":573},{"source":527,"target":366},{"source":459,"target":532},{"source":527,"target":532},{"source":377,"target":532},{"source":529,"target":532},{"source":528,"target":532},{"source":527,"target":519},{"source":527,"target":213},{"source":527,"target":327},{"source":212,"target":527},{"source":526,"target":527},{"source":457,"target":527},{"source":359,"target":527},{"source":293,"target":527},{"source":211,"target":527},{"source":506,"target":521},{"source":573,"target":509},{"source":320,"target":506},{"source":533,"target":506},{"source":210,"target":506},{"source":460,"target":506},{"source":325,"target":506},{"source":536,"target":506},{"source":434,"target":209},{"source":395,"target":208},{"source":537,"target":370},{"source":207,"target":206},{"source":205,"target":204},{"source":324,"target":203},{"source":321,"target":537},{"source":324,"target":537},{"source":520,"target":537},{"source":292,"target":537},{"source":377,"target":537},{"source":202,"target":513},{"source":201,"target":513},{"source":335,"target":328},{"source":200,"target":328},{"source":466,"target":249},{"source":199,"target":249},{"source":536,"target":534},{"source":520,"target":332},{"source":536,"target":332},{"source":460,"target":575},{"source":527,"target":575},{"source":377,"target":575},{"source":561,"target":324},{"source":520,"target":531},{"source":536,"target":320},{"source":476,"target":500},{"source":198,"target":500},{"source":422,"target":500},{"source":197,"target":500},{"source":488,"target":196},{"source":195,"target":492},{"source":194,"target":492},{"source":195,"target":193},{"source":192,"target":191},{"source":192,"target":190},{"source":189,"target":192},{"source":188,"target":195},{"source":189,"target":195},{"source":187,"target":195},{"source":186,"target":195},{"source":185,"target":195},{"source":184,"target":195},{"source":183,"target":188},{"source":186,"target":182},{"source":200,"target":181},{"source":456,"target":180},{"source":179,"target":178},{"source":468,"target":335},{"source":386,"target":335},{"source":536,"target":366},{"source":177,"target":366},{"source":536,"target":561},{"source":176,"target":175},{"source":298,"target":175},{"source":174,"target":175},{"source":547,"target":173},{"source":469,"target":179},{"source":172,"target":488},{"source":171,"target":488},{"source":382,"target":488},{"source":197,"target":476},{"source":170,"target":476},{"source":382,"target":476},{"source":469,"target":183},{"source":456,"target":183},{"source":429,"target":183},{"source":434,"target":482},{"source":468,"target":470},{"source":286,"target":470},{"source":266,"target":470},{"source":395,"target":470},{"source":200,"target":470},{"source":169,"target":469},{"source":168,"target":469},{"source":297,"target":468},{"source":266,"target":468},{"source":200,"target":468},{"source":386,"target":468},{"source":257,"target":468},{"source":167,"target":352},{"source":520,"target":459},{"source":529,"target":459},{"source":529,"target":559},{"source":536,"target":520},{"source":529,"target":520},{"source":528,"target":520},{"source":376,"target":520},{"source":557,"target":520},{"source":457,"target":520},{"source":547,"target":520},{"source":166,"target":520},{"source":429,"target":194},{"source":387,"target":165},{"source":342,"target":462},{"source":164,"target":345},{"source":432,"target":345},{"source":536,"target":212},{"source":163,"target":162},{"source":313,"target":162},{"source":529,"target":526},{"source":542,"target":161},{"source":238,"target":199},{"source":290,"target":536},{"source":458,"target":536},{"source":376,"target":536},{"source":382,"target":160},{"source":434,"target":159},{"source":224,"target":159},{"source":158,"target":214},{"source":158,"target":445},{"source":158,"target":436},{"source":166,"target":367},{"source":447,"target":158},{"source":353,"target":158},{"source":166,"target":158},{"source":157,"target":156},{"source":434,"target":155},{"source":342,"target":155},{"source":351,"target":434},{"source":226,"target":434},{"source":503,"target":434},{"source":224,"target":434},{"source":211,"target":560},{"source":390,"target":429},{"source":154,"target":426},{"source":412,"target":426},{"source":197,"target":426},{"source":153,"target":426},{"source":224,"target":351},{"source":167,"target":351},{"source":422,"target":198},{"source":197,"target":198},{"source":342,"target":226},{"source":253,"target":226},{"source":542,"target":514},{"source":224,"target":514},{"source":286,"target":475},{"source":287,"target":286},{"source":285,"target":313},{"source":287,"target":313},{"source":549,"target":529},{"source":359,"target":529},{"source":242,"target":416},{"source":224,"target":416},{"source":349,"target":342},{"source":463,"target":342},{"source":239,"target":342},{"source":542,"target":342},{"source":238,"target":342},{"source":211,"target":557},{"source":197,"target":412},{"source":153,"target":412},{"source":152,"target":412},{"source":151,"target":279},{"source":277,"target":297},{"source":382,"target":422},{"source":542,"target":150},{"source":166,"target":360},{"source":293,"target":339},{"source":432,"target":551},{"source":149,"target":148},{"source":147,"target":197},{"source":146,"target":197},{"source":153,"target":197},{"source":224,"target":145},{"source":224,"target":548},{"source":211,"target":144},{"source":542,"target":349},{"source":242,"target":455},{"source":242,"target":143},{"source":142,"target":396},{"source":395,"target":268},{"source":386,"target":266},{"source":386,"target":141},{"source":542,"target":253},{"source":167,"target":239},{"source":399,"target":395},{"source":142,"target":140},{"source":139,"target":147},{"source":277,"target":151},{"source":224,"target":473},{"source":399,"target":138},{"source":276,"target":287},{"source":277,"target":137},{"source":224,"target":454},{"source":390,"target":136},{"source":135,"target":136},{"source":142,"target":149},{"source":256,"target":399},{"source":134,"target":277},{"source":394,"target":277},{"source":542,"target":423},{"source":224,"target":453},{"source":224,"target":414},{"source":542,"target":133},{"source":224,"target":542},{"source":452,"target":224},{"source":293,"target":541},{"source":167,"target":132},{"source":272,"target":305},{"source":200,"target":304},{"source":135,"target":304},{"source":168,"target":304},{"source":168,"target":169},{"source":386,"target":169},{"source":168,"target":200},{"source":386,"target":394},{"source":168,"target":135},{"source":386,"target":135},{"source":272,"target":135},{"source":211,"target":293},{"source":131,"target":130},{"source":517,"target":129},{"source":129,"target":521},{"source":128,"target":204},{"source":128,"target":516},{"source":572,"target":128},{"source":129,"target":319},{"source":129,"target":536},{"source":531,"target":522},{"source":366,"target":522},{"source":354,"target":127},{"source":507,"target":126},{"source":570,"target":126},{"source":377,"target":534},{"source":533,"target":568},{"source":570,"target":322},{"source":320,"target":531},{"source":570,"target":531},{"source":526,"target":531},{"source":377,"target":531},{"source":376,"target":531},{"source":365,"target":366},{"source":526,"target":366},{"source":294,"target":125},{"source":212,"target":327},{"source":377,"target":326},{"source":300,"target":212},{"source":376,"target":377},{"source":364,"target":377},{"source":293,"target":377},{"source":354,"target":124},{"source":354,"target":331},{"source":123,"target":122},{"source":243,"target":121},{"source":229,"target":121},{"source":359,"target":559},{"source":359,"target":558},{"source":359,"target":237},{"source":359,"target":344},{"source":435,"target":449},{"source":359,"target":341},{"source":241,"target":359},{"source":120,"target":540},{"source":120,"target":119},{"source":118,"target":506},{"source":236,"target":209},{"source":535,"target":521},{"source":526,"target":538},{"source":295,"target":538},{"source":532,"target":539},{"source":529,"target":539},{"source":547,"target":539},{"source":117,"target":176},{"source":239,"target":116},{"source":117,"target":465},{"source":341,"target":352},{"source":455,"target":161},{"source":407,"target":231},{"source":115,"target":231},{"source":413,"target":231},{"source":435,"target":114},{"source":113,"target":112},{"source":131,"target":111},{"source":110,"target":439},{"source":435,"target":439},{"source":233,"target":109},{"source":341,"target":108},{"source":548,"target":269},{"source":107,"target":415},{"source":398,"target":341},{"source":423,"target":341},{"source":402,"target":107},{"source":401,"target":107},{"source":106,"target":107},{"source":238,"target":239},{"source":413,"target":239},{"source":106,"target":402},{"source":105,"target":115},{"source":104,"target":373},{"source":522,"target":103},{"source":561,"target":534},{"source":245,"target":534},{"source":361,"target":534},{"source":554,"target":534},{"source":339,"target":534},{"source":547,"target":534},{"source":293,"target":534},{"source":505,"target":561},{"source":430,"target":505},{"source":557,"target":505},{"source":293,"target":213},{"source":449,"target":102},{"source":438,"target":102},{"source":356,"target":102},{"source":436,"target":102},{"source":101,"target":445},{"source":353,"target":100},{"source":124,"target":436},{"source":124,"target":99},{"source":353,"target":124},{"source":353,"target":222},{"source":101,"target":98},{"source":101,"target":217},{"source":97,"target":353},{"source":378,"target":255},{"source":378,"target":459},{"source":378,"target":520},{"source":378,"target":527},{"source":536,"target":378},{"source":569,"target":378},{"source":366,"target":521},{"source":459,"target":521},{"source":529,"target":521},{"source":211,"target":521},{"source":333,"target":540},{"source":554,"target":254},{"source":516,"target":204},{"source":342,"target":96},{"source":333,"target":531},{"source":508,"target":530},{"source":529,"target":530},{"source":141,"target":95},{"source":193,"target":94},{"source":93,"target":94},{"source":92,"target":94},{"source":499,"target":193},{"source":91,"target":193},{"source":190,"target":191},{"source":189,"target":191},{"source":429,"target":90},{"source":185,"target":90},{"source":89,"target":91},{"source":178,"target":88},{"source":141,"target":335},{"source":470,"target":87},{"source":268,"target":87},{"source":86,"target":85},{"source":260,"target":84},{"source":83,"target":470},{"source":82,"target":470},{"source":81,"target":470},{"source":80,"target":470},{"source":528,"target":508},{"source":339,"target":558},{"source":404,"target":558},{"source":554,"target":556},{"source":546,"target":556},{"source":339,"target":462},{"source":325,"target":519},{"source":333,"target":527},{"source":554,"target":232},{"source":349,"target":554},{"source":543,"target":554},{"source":253,"target":554},{"source":541,"target":554},{"source":339,"target":552},{"source":404,"target":552},{"source":546,"target":552},{"source":339,"target":430},{"source":185,"target":81},{"source":475,"target":185},{"source":184,"target":185},{"source":141,"target":185},{"source":141,"target":422},{"source":349,"target":339},{"source":143,"target":339},{"source":224,"target":339},{"source":79,"target":78},{"source":404,"target":164},{"source":404,"target":143},{"source":224,"target":404},{"source":241,"target":404},{"source":77,"target":141},{"source":489,"target":141},{"source":541,"target":253},{"source":137,"target":400},{"source":76,"target":400},{"source":75,"target":149},{"source":260,"target":149},{"source":74,"target":73},{"source":427,"target":73},{"source":260,"target":73},{"source":260,"target":74},{"source":541,"target":228},{"source":241,"target":541},{"source":72,"target":71},{"source":569,"target":539},{"source":70,"target":562},{"source":324,"target":371},{"source":564,"target":556},{"source":564,"target":554},{"source":357,"target":69},{"source":447,"target":69},{"source":436,"target":100},{"source":98,"target":438},{"source":543,"target":560},{"source":557,"target":351},{"source":557,"target":350},{"source":557,"target":549},{"source":349,"target":557},{"source":404,"target":557},{"source":228,"target":557},{"source":241,"target":557},{"source":564,"target":547},{"source":253,"target":564},{"source":544,"target":564},{"source":293,"target":564},{"source":127,"target":68},{"source":238,"target":328},{"source":458,"target":534},{"source":67,"target":66},{"source":459,"target":561},{"source":458,"target":505},{"source":65,"target":64},{"source":63,"target":183},{"source":238,"target":469},{"source":325,"target":459},{"source":526,"target":459},{"source":528,"target":459},{"source":457,"target":459},{"source":528,"target":559},{"source":569,"target":62},{"source":362,"target":125},{"source":458,"target":327},{"source":528,"target":362},{"source":564,"target":362},{"source":458,"target":526},{"source":528,"target":377},{"source":439,"target":114},{"source":61,"target":112},{"source":60,"target":439},{"source":358,"target":69},{"source":358,"target":449},{"source":369,"target":449},{"source":367,"target":449},{"source":217,"target":358},{"source":369,"target":445},{"source":367,"target":437},{"source":367,"target":436},{"source":220,"target":367},{"source":416,"target":61},{"source":59,"target":61},{"source":59,"target":58},{"source":289,"target":57},{"source":376,"target":57},{"source":457,"target":528},{"source":360,"target":528},{"source":421,"target":416},{"source":419,"target":416},{"source":145,"target":416},{"source":406,"target":416},{"source":287,"target":416},{"source":398,"target":416},{"source":423,"target":416},{"source":413,"target":407},{"source":145,"target":419},{"source":277,"target":145},{"source":417,"target":145},{"source":56,"target":145},{"source":275,"target":145},{"source":401,"target":63},{"source":55,"target":63},{"source":452,"target":415},{"source":238,"target":402},{"source":413,"target":402},{"source":319,"target":531},{"source":570,"target":319},{"source":536,"target":319},{"source":506,"target":540},{"source":54,"target":53},{"source":128,"target":509},{"source":506,"target":509},{"source":506,"target":531},{"source":378,"target":506},{"source":129,"target":506},{"source":52,"target":248},{"source":99,"target":363},{"source":434,"target":51},{"source":224,"target":51},{"source":50,"target":49},{"source":241,"target":48},{"source":550,"target":50},{"source":545,"target":446},{"source":241,"target":164},{"source":545,"target":423},{"source":542,"target":545},{"source":510,"target":523},{"source":47,"target":46},{"source":561,"target":219},{"source":232,"target":561},{"source":554,"target":561},{"source":552,"target":561},{"source":547,"target":552},{"source":443,"target":214},{"source":445,"target":214},{"source":443,"target":449},{"source":438,"target":445},{"source":547,"target":549},{"source":546,"target":547},{"source":295,"target":534},{"source":526,"target":332},{"source":290,"target":332},{"source":564,"target":332},{"source":365,"target":561},{"source":526,"target":561},{"source":360,"target":561},{"source":216,"target":365},{"source":326,"target":213},{"source":295,"target":213},{"source":295,"target":327},{"source":360,"target":326},{"source":364,"target":325},{"source":557,"target":526},{"source":457,"target":526},{"source":295,"target":526},{"source":360,"target":526},{"source":564,"target":526},{"source":544,"target":526},{"source":331,"target":357},{"source":331,"target":214},{"source":331,"target":445},{"source":97,"target":331},{"source":564,"target":295},{"source":359,"target":295},{"source":522,"target":540},{"source":520,"target":540},{"source":527,"target":540},{"source":377,"target":540},{"source":529,"target":540},{"source":528,"target":540},{"source":573,"target":371},{"source":527,"target":537},{"source":528,"target":573},{"source":532,"target":366},{"source":532,"target":561},{"source":526,"target":532},{"source":458,"target":532},{"source":211,"target":532},{"source":527,"target":326},{"source":458,"target":527},{"source":45,"target":119},{"source":349,"target":209},{"source":166,"target":537},{"source":128,"target":573},{"source":536,"target":531},{"source":44,"target":317},{"source":129,"target":538},{"source":550,"target":502},{"source":174,"target":43},{"source":85,"target":512},{"source":42,"target":492},{"source":189,"target":41},{"source":485,"target":41},{"source":42,"target":195},{"source":174,"target":195},{"source":194,"target":42},{"source":429,"target":42},{"source":140,"target":42},{"source":92,"target":188},{"source":92,"target":484},{"source":335,"target":312},{"source":310,"target":312},{"source":310,"target":335},{"source":395,"target":311},{"source":303,"target":310},{"source":40,"target":310},{"source":469,"target":310},{"source":468,"target":310},{"source":141,"target":310},{"source":80,"target":310},{"source":417,"target":310},{"source":386,"target":310},{"source":155,"target":176},{"source":469,"target":303},{"source":401,"target":183},{"source":401,"target":302},{"source":296,"target":302},{"source":427,"target":84},{"source":489,"target":84},{"source":92,"target":93},{"source":253,"target":352},{"source":339,"target":559},{"source":211,"target":559},{"source":560,"target":520},{"source":293,"target":520},{"source":39,"target":165},{"source":549,"target":556},{"source":222,"target":363},{"source":339,"target":344},{"source":288,"target":86},{"source":529,"target":377},{"source":528,"target":536},{"source":81,"target":38},{"source":155,"target":159},{"source":239,"target":159},{"source":356,"target":69},{"source":158,"target":69},{"source":217,"target":443},{"source":97,"target":100},{"source":222,"target":438},{"source":447,"target":356},{"source":355,"target":356},{"source":217,"target":436},{"source":355,"target":436},{"source":217,"target":447},{"source":220,"target":447},{"source":355,"target":220},{"source":406,"target":108},{"source":138,"target":108},{"source":76,"target":108},{"source":421,"target":155},{"source":455,"target":155},{"source":402,"target":155},{"source":423,"target":155},{"source":432,"target":155},{"source":529,"target":504},{"source":529,"target":560},{"source":457,"target":560},{"source":453,"target":456},{"source":253,"target":550},{"source":401,"target":37},{"source":541,"target":346},{"source":289,"target":290},{"source":475,"target":81},{"source":296,"target":286},{"source":360,"target":529},{"source":339,"target":529},{"source":541,"target":529},{"source":211,"target":458},{"source":133,"target":416},{"source":143,"target":446},{"source":549,"target":350},{"source":339,"target":350},{"source":541,"target":549},{"source":457,"target":557},{"source":401,"target":36},{"source":293,"target":457},{"source":463,"target":150},{"source":211,"target":295},{"source":273,"target":406},{"source":277,"target":406},{"source":35,"target":34},{"source":164,"target":548},{"source":349,"target":548},{"source":278,"target":33},{"source":239,"target":253},{"source":139,"target":32},{"source":305,"target":32},{"source":417,"target":137},{"source":417,"target":278},{"source":75,"target":31},{"source":74,"target":31},{"source":30,"target":149},{"source":427,"target":29},{"source":56,"target":399},{"source":401,"target":277},{"source":56,"target":276},{"source":168,"target":401},{"source":275,"target":401},{"source":262,"target":401},{"source":168,"target":296},{"source":388,"target":28},{"source":262,"target":453},{"source":39,"target":27},{"source":56,"target":417},{"source":30,"target":142},{"source":75,"target":389},{"source":75,"target":387},{"source":427,"target":74},{"source":72,"target":26},{"source":169,"target":265},{"source":168,"target":265},{"source":380,"target":305},{"source":275,"target":394},{"source":25,"target":157},{"source":528,"target":378},{"source":173,"target":539},{"source":570,"target":539},{"source":504,"target":539},{"source":570,"target":534},{"source":212,"target":534},{"source":533,"target":507},{"source":533,"target":531},{"source":561,"target":531},{"source":505,"target":531},{"source":570,"target":505},{"source":290,"target":570},{"source":326,"target":125},{"source":295,"target":377},{"source":360,"target":377},{"source":293,"target":559},{"source":293,"target":555},{"source":293,"target":241},{"source":65,"target":252},{"source":544,"target":53},{"source":232,"target":249},{"source":552,"target":245},{"source":232,"target":246},{"source":237,"target":558},{"source":551,"target":558},{"source":237,"target":556},{"source":434,"target":556},{"source":342,"target":556},{"source":253,"target":556},{"source":544,"target":556},{"source":159,"target":237},{"source":155,"target":237},{"source":143,"target":237},{"source":423,"target":237},{"source":432,"target":237},{"source":223,"target":237},{"source":228,"target":237},{"source":542,"target":237},{"source":438,"target":363},{"source":241,"target":555},{"source":111,"target":444},{"source":48,"target":444},{"source":543,"target":552},{"source":544,"target":349},{"source":481,"target":543},{"source":545,"target":223},{"source":521,"target":375},{"source":328,"target":209},{"source":103,"target":521},{"source":531,"target":521},{"source":517,"target":575},{"source":493,"target":244},{"source":377,"target":508},{"source":340,"target":462},{"source":423,"target":462},{"source":503,"target":416},{"source":24,"target":446},{"source":423,"target":446},{"source":432,"target":446},{"source":503,"target":421},{"source":455,"target":410},{"source":503,"target":145},{"source":463,"target":455},{"source":432,"target":455},{"source":238,"target":455},{"source":402,"target":463},{"source":56,"target":463},{"source":390,"target":463},{"source":277,"target":503},{"source":402,"target":503},{"source":378,"target":575},{"source":534,"target":567},{"source":104,"target":372},{"source":23,"target":522},{"source":364,"target":534},{"source":359,"target":534},{"source":547,"target":505},{"source":124,"target":363},{"source":357,"target":102},{"source":214,"target":102},{"source":445,"target":102},{"source":447,"target":102},{"source":101,"target":102},{"source":101,"target":124},{"source":353,"target":355},{"source":46,"target":203},{"source":135,"target":94},{"source":219,"target":251},{"source":141,"target":469},{"source":141,"target":22},{"source":449,"target":363},{"source":437,"target":363},{"source":449,"target":214},{"source":447,"target":449},{"source":21,"target":20},{"source":33,"target":268},{"source":137,"target":33},{"source":135,"target":141},{"source":19,"target":140},{"source":149,"target":140},{"source":18,"target":140},{"source":260,"target":140},{"source":17,"target":140},{"source":263,"target":138},{"source":541,"target":359},{"source":16,"target":388},{"source":459,"target":534},{"source":362,"target":534},{"source":528,"target":533},{"source":459,"target":366},{"source":528,"target":561},{"source":528,"target":505},{"source":528,"target":570},{"source":377,"target":459},{"source":458,"target":459},{"source":362,"target":326},{"source":528,"target":361},{"source":362,"target":212},{"source":377,"target":362},{"source":358,"target":102},{"source":369,"target":69},{"source":358,"target":214},{"source":331,"target":358},{"source":369,"target":443},{"source":438,"target":369},{"source":354,"target":367},{"source":101,"target":367},{"source":353,"target":367},{"source":97,"target":367},{"source":528,"target":458},{"source":295,"target":458},{"source":376,"target":528},{"source":557,"target":528},{"source":295,"target":528},{"source":342,"target":352},{"source":463,"target":345},{"source":342,"target":159},{"source":342,"target":434},{"source":349,"target":434},{"source":253,"target":434},{"source":542,"target":434},{"source":551,"target":525},{"source":349,"target":351},{"source":132,"target":226},{"source":548,"target":342},{"source":224,"target":342},{"source":224,"target":551},{"source":224,"target":455},{"source":242,"target":463},{"source":224,"target":503},{"source":167,"target":253},{"source":432,"target":242},{"source":368,"target":206},{"source":23,"target":568},{"source":557,"target":558},{"source":557,"target":237},{"source":100,"target":363},{"source":557,"target":344},{"source":214,"target":69},{"source":445,"target":69},{"source":436,"target":69},{"source":98,"target":449},{"source":98,"target":437},{"source":564,"target":342},{"source":564,"target":557},{"source":224,"target":557},{"source":527,"target":521},{"source":366,"target":540},{"source":459,"target":540},{"source":527,"target":574},{"source":573,"target":516},{"source":531,"target":573},{"source":533,"target":573},{"source":527,"target":531},{"source":532,"target":570},{"source":508,"target":532},{"source":377,"target":527},{"source":536,"target":527},{"source":529,"target":527},{"source":528,"target":527},{"source":376,"target":527},{"source":295,"target":527},{"source":329,"target":334},{"source":526,"target":522},{"source":96,"target":250},{"source":96,"target":53},{"source":315,"target":317},{"source":197,"target":15},{"source":491,"target":14},{"source":484,"target":491},{"source":488,"target":491},{"source":93,"target":491},{"source":428,"target":491},{"source":298,"target":42},{"source":488,"target":484},{"source":93,"target":484},{"source":382,"target":484},{"source":200,"target":329},{"source":428,"target":488},{"source":93,"target":474},{"source":376,"target":365},{"source":298,"target":468},{"source":339,"target":237},{"source":404,"target":237},{"source":292,"target":213},{"source":327,"target":215},{"source":326,"target":327},{"source":295,"target":326},{"source":333,"target":378},{"source":554,"target":480},{"source":544,"target":554},{"source":331,"target":436},{"source":331,"target":447},{"source":220,"target":331},{"source":13,"target":426},{"source":339,"target":550},{"source":280,"target":12},{"source":34,"target":12},{"source":411,"target":441},{"source":423,"target":201},{"source":13,"target":412},{"source":406,"target":421},{"source":264,"target":421},{"source":402,"target":421},{"source":417,"target":421},{"source":56,"target":421},{"source":422,"target":411},{"source":382,"target":411},{"source":551,"target":339},{"source":341,"target":339},{"source":541,"target":339},{"source":419,"target":78},{"source":406,"target":419},{"source":454,"target":406},{"source":541,"target":349},{"source":261,"target":140},{"source":398,"target":454},{"source":262,"target":402},{"source":401,"target":423},{"source":452,"target":423},{"source":452,"target":11},{"source":392,"target":387},{"source":384,"target":387},{"source":392,"target":13},{"source":383,"target":392},{"source":383,"target":384},{"source":378,"target":540},{"source":537,"target":371},{"source":531,"target":537},{"source":326,"target":537},{"source":536,"target":507},{"source":536,"target":533},{"source":536,"target":570},{"source":536,"target":365},{"source":326,"target":520},{"source":362,"target":520},{"source":377,"target":520},{"source":295,"target":520},{"source":529,"target":362},{"source":158,"target":102},{"source":158,"target":356},{"source":331,"target":158},{"source":355,"target":158},{"source":458,"target":529},{"source":528,"target":529},{"source":457,"target":529},{"source":293,"target":529},{"source":246,"target":561},{"source":547,"target":561},{"source":517,"target":62},{"source":553,"target":554},{"source":443,"target":357},{"source":445,"target":357},{"source":447,"target":443},{"source":572,"target":573},{"source":572,"target":507},{"source":570,"target":572},{"source":210,"target":539},{"source":508,"target":539},{"source":548,"target":352},{"source":575,"target":509},{"source":376,"target":559},{"source":376,"target":361},{"source":217,"target":69},{"source":217,"target":357},{"source":222,"target":214},{"source":222,"target":449},{"source":222,"target":443},{"source":355,"target":443},{"source":356,"target":445},{"source":355,"target":445},{"source":220,"target":100},{"source":217,"target":438},{"source":217,"target":356},{"source":222,"target":437},{"source":220,"target":222},{"source":97,"target":222},{"source":355,"target":98},{"source":457,"target":376},{"source":10,"target":53},{"source":531,"target":534},{"source":533,"target":534},{"source":366,"target":534},{"source":533,"target":322},{"source":366,"target":507},{"source":570,"target":507},{"source":365,"target":531},{"source":325,"target":531},{"source":506,"target":319},{"source":570,"target":533},{"source":9,"target":90},{"source":570,"target":366},{"source":377,"target":561},{"source":489,"target":8},{"source":526,"target":570},{"source":377,"target":570},{"source":457,"target":570},{"source":360,"target":570},{"source":212,"target":213},{"source":457,"target":377},{"source":545,"target":155},{"source":77,"target":37},{"source":545,"target":143},{"source":545,"target":463},{"source":76,"target":137},{"source":17,"target":29},{"source":545,"target":432},{"source":17,"target":427},{"source":130,"target":35},{"source":7,"target":425},{"source":177,"target":508},{"source":529,"target":508},{"source":541,"target":559},{"source":447,"target":438},{"source":241,"target":350},{"source":339,"target":549},{"source":533,"target":319},{"source":470,"target":328},{"source":469,"target":328},{"source":192,"target":193},{"source":195,"target":191},{"source":195,"target":190},{"source":195,"target":192},{"source":304,"target":179},{"source":200,"target":179},{"source":194,"target":183},{"source":468,"target":469},{"source":386,"target":469},{"source":141,"target":468},{"source":429,"target":456},{"source":395,"target":33},{"source":394,"target":266},{"source":272,"target":140},{"source":277,"target":77},{"source":276,"target":399},{"source":386,"target":277},{"source":6,"target":169},{"source":386,"target":200},{"source":386,"target":168},{"source":5,"target":103},{"source":568,"target":522},{"source":568,"target":534},{"source":376,"target":534},{"source":557,"target":534},{"source":457,"target":534},{"source":564,"target":534},{"source":437,"target":102},{"source":124,"target":449},{"source":124,"target":443},{"source":124,"target":438},{"source":353,"target":356},{"source":124,"target":437},{"source":447,"target":124},{"source":333,"target":129},{"source":528,"target":534},{"source":528,"target":531},{"source":459,"target":570},{"source":238,"target":310},{"source":238,"target":470},{"source":333,"target":62},{"source":293,"target":362},{"source":67,"target":112},{"source":367,"target":357},{"source":369,"target":214},{"source":367,"target":214},{"source":222,"target":358},{"source":98,"target":358},{"source":437,"target":369},{"source":447,"target":369},{"source":98,"target":369},{"source":355,"target":369},{"source":367,"target":356},{"source":447,"target":367},{"source":399,"target":416},{"source":56,"target":416},{"source":473,"target":281},{"source":454,"target":145},{"source":402,"target":415},{"source":423,"target":415},{"source":262,"target":415},{"source":531,"target":540},{"source":573,"target":537},{"source":564,"target":527},{"source":143,"target":462},{"source":129,"target":527},{"source":446,"target":155},{"source":143,"target":155},{"source":463,"target":155},{"source":413,"target":155},{"source":58,"target":21},{"source":253,"target":349},{"source":463,"target":143},{"source":238,"target":253},{"source":556,"target":352},{"source":543,"target":556},{"source":481,"target":556},{"source":237,"target":462},{"source":228,"target":462},{"source":228,"target":143},{"source":239,"target":481},{"source":224,"target":228},{"source":544,"target":542},{"source":333,"target":575},{"source":449,"target":357},{"source":437,"target":357},{"source":438,"target":449},{"source":447,"target":437},{"source":562,"target":523},{"source":557,"target":559},{"source":98,"target":69},{"source":98,"target":214},{"source":100,"target":443},{"source":438,"target":100},{"source":437,"target":100},{"source":447,"target":100},{"source":293,"target":560},{"source":359,"target":557},{"source":541,"target":557},{"source":293,"target":557},{"source":526,"target":534},{"source":504,"target":505},{"source":221,"target":326},{"source":295,"target":361},{"source":518,"target":325},{"source":331,"target":69},{"source":331,"target":437},{"source":4,"target":289},{"source":295,"target":557},{"source":295,"target":457},{"source":293,"target":295},{"source":520,"target":534},{"source":158,"target":100},{"source":98,"target":158},{"source":217,"target":158},{"source":96,"target":10},{"source":554,"target":96},{"source":62,"target":575},{"source":366,"target":531},{"source":333,"target":506},{"source":187,"target":191},{"source":499,"target":14},{"source":561,"target":366},{"source":570,"target":561},{"source":553,"target":561},{"source":553,"target":245},{"source":470,"target":310},{"source":147,"target":476},{"source":268,"target":470},{"source":141,"target":470},{"source":394,"target":470},{"source":339,"target":556},{"source":446,"target":462},{"source":463,"target":462},{"source":432,"target":462},{"source":414,"target":462},{"source":125,"target":213},{"source":125,"target":215},{"source":327,"target":125},{"source":292,"target":125},{"source":355,"target":69},{"source":222,"target":357},{"source":438,"target":214},{"source":445,"target":449},{"source":222,"target":445},{"source":220,"target":445},{"source":356,"target":100},{"source":217,"target":100},{"source":222,"target":356},{"source":220,"target":356},{"source":222,"target":436},{"source":447,"target":222},{"source":217,"target":98},{"source":97,"target":355},{"source":267,"target":108},{"source":342,"target":351},{"source":383,"target":424},{"source":287,"target":283},{"source":408,"target":420},{"source":463,"target":416},{"source":541,"target":342},{"source":228,"target":339},{"source":241,"target":339},{"source":271,"target":78},{"source":266,"target":406},{"source":399,"target":406},{"source":56,"target":406},{"source":423,"target":455},{"source":503,"target":463},{"source":423,"target":463},{"source":263,"target":268},{"source":394,"target":268},{"source":56,"target":503},{"source":546,"target":543},{"source":30,"target":140},{"source":414,"target":393},{"source":29,"target":149},{"source":417,"target":277},{"source":56,"target":277},{"source":275,"target":277},{"source":432,"target":423},{"source":224,"target":423},{"source":544,"target":546},{"source":427,"target":13},{"source":260,"target":427},{"source":392,"target":427},{"source":17,"target":260},{"source":275,"target":386},{"source":506,"target":575},{"source":527,"target":520},{"source":362,"target":213},{"source":362,"target":292},{"source":295,"target":362},{"source":367,"target":69},{"source":369,"target":357},{"source":100,"target":358},{"source":217,"target":367},{"source":215,"target":213},{"source":98,"target":102},{"source":355,"target":102},{"source":124,"target":69},{"source":124,"target":357},{"source":124,"target":214},{"source":124,"target":445},{"source":124,"target":356},{"source":355,"target":124},{"source":447,"target":214},{"source":99,"target":436},{"source":404,"target":350},{"source":224,"target":545},{"source":527,"target":538},{"source":505,"target":539},{"source":236,"target":58},{"source":329,"target":335},{"source":292,"target":327},{"source":230,"target":3},{"source":331,"target":102},{"source":331,"target":443},{"source":331,"target":356},{"source":353,"target":331},{"source":395,"target":316},{"source":423,"target":454},{"source":423,"target":402},{"source":401,"target":402},{"source":56,"target":423},{"source":510,"target":562},{"source":100,"target":69},{"source":100,"target":357},{"source":98,"target":357},{"source":98,"target":443},{"source":339,"target":557},{"source":469,"target":335},{"source":437,"target":449},{"source":437,"target":438},{"source":359,"target":339},{"source":260,"target":18},{"source":258,"target":260},{"source":508,"target":366},{"source":5,"target":252},{"source":545,"target":237},{"source":377,"target":366},{"source":84,"target":188},{"source":220,"target":98},{"source":503,"target":155},{"source":432,"target":143},{"source":75,"target":388},{"source":26,"target":35},{"source":362,"target":527},{"source":122,"target":566},{"source":245,"target":561},{"source":447,"target":445},{"source":378,"target":62},{"source":367,"target":358},{"source":367,"target":443},{"source":367,"target":445},{"source":100,"target":369},{"source":217,"target":369},{"source":454,"target":416},{"source":544,"target":96},{"source":541,"target":351},{"source":217,"target":102},{"source":200,"target":335},{"source":422,"target":476},{"source":200,"target":469},{"source":224,"target":462},{"source":158,"target":369},{"source":557,"target":529},{"source":295,"target":529},{"source":211,"target":529},{"source":224,"target":446},{"source":253,"target":342},{"source":167,"target":342},{"source":224,"target":463},{"source":266,"target":268},{"source":170,"target":147},{"source":139,"target":170},{"source":168,"target":277},{"source":224,"target":432},{"source":327,"target":213},{"source":331,"target":100},{"source":331,"target":124},{"source":331,"target":98},{"source":355,"target":331},{"source":209,"target":334},{"source":423,"target":503},{"source":100,"target":214},{"source":100,"target":449},{"source":100,"target":445},{"source":10,"target":250},{"source":189,"target":190},{"source":527,"target":534},{"source":60,"target":2},{"source":222,"target":69},{"source":355,"target":100},{"source":98,"target":356},{"source":217,"target":437},{"source":98,"target":222},{"source":174,"target":185},{"source":362,"target":327},{"source":369,"target":102},{"source":367,"target":102},{"source":369,"target":358},{"source":124,"target":369},{"source":98,"target":367},{"source":355,"target":367},{"source":224,"target":237},{"source":438,"target":357},{"source":445,"target":443},{"source":69,"target":102},{"source":222,"target":102},{"source":158,"target":367},{"source":158,"target":222},{"source":328,"target":334},{"source":470,"target":335},{"source":27,"target":1},{"source":25,"target":1},{"source":56,"target":454},{"source":25,"target":27},{"source":0,"target":153},{"source":0,"target":25},{"source":384,"target":392},{"source":98,"target":445},{"source":98,"target":100},{"source":333,"target":517},{"source":447,"target":357},{"source":224,"target":155},{"source":224,"target":143},{"source":124,"target":358},{"source":222,"target":369},{"source":331,"target":369},{"source":401,"target":415},{"source":217,"target":222},{"source":355,"target":222},{"source":469,"target":470},{"source":158,"target":358},{"source":53,"target":250},{"source":100,"target":102},{"source":124,"target":102},{"source":98,"target":124},{"source":217,"target":124},{"source":331,"target":217},{"source":540,"target":521},{"source":214,"target":357},{"source":98,"target":447},{"source":367,"target":100},{"source":222,"target":100},{"source":158,"target":124},{"source":124,"target":100},{"source":331,"target":222},{"source":367,"target":369},{"source":124,"target":367},{"source":222,"target":367},{"source":331,"target":367},{"source":432,"target":463},{"source":222,"target":124}]
